setup.py
django_host_settings/__init__.py
django_host_settings/settings.py
django_host_settings.egg-info/PKG-INFO
django_host_settings.egg-info/SOURCES.txt
django_host_settings.egg-info/dependency_links.txt
django_host_settings.egg-info/not-zip-safe
django_host_settings.egg-info/top_level.txt
django_host_settings/management/__init__.py
django_host_settings/management/commands/__init__.py
django_host_settings/management/commands/createhostsettings.py