Metadata-Version: 1.0
Name: django-host-settings
Version: 0.2
Summary: A small Django app for managing local settings files for multiple hosts
Home-page: https://github.com/sandersnewmedia/django-host-settings
Author: Elijah Rutschman
Author-email: elijah@sandersnewmedia.com
License: UNKNOWN
Platform: UNKNOWN
